{
  "n_runs_per_entity": 5,
  "per_entity": {
    "amalia_rodrigues": {
      "event_driven": {
        "n": 5,
        "bertscore": {
          "mean": 0.8220924258232116,
          "variance": 3.5739885087693327e-05,
          "std": 0.0059782844602522325,
          "values": [
            0.8144699931144714,
            0.8291386365890503,
            0.8265562653541565,
            0.822114109992981,
            0.8181831240653992
          ]
        },
        "lexical_recall": {
          "mean": 0.04924951751416627,
          "variance": 7.271760012167893e-05,
          "std": 0.008527461528595653,
          "values": [
            0.045662100456621,
            0.04100946372239748,
            0.044444444444444446,
            0.0625,
            0.05263157894736842
          ]
        },
        "title_cov": {
          "mean": 0.0,
          "variance": 0.0,
          "std": 0.0,
          "values": [
            0.0,
            0.0,
            0.0,
            0.0,
            0.0
          ]
        },
        "noloop": {
          "mean": 0.8751627051499717,
          "variance": 0.003597789515471572,
          "std": 0.05998157646704171,
          "values": [
            0.8888888888888888,
            0.9375,
            0.868421052631579,
            0.7777777777777778,
            0.9032258064516129
          ]
        },
        "ctx_recall": {
          "mean": 0.04924951751416627,
          "variance": 7.271760012167893e-05,
          "std": 0.008527461528595653,
          "values": [
            0.045662100456621,
            0.04100946372239748,
            0.044444444444444446,
            0.0625,
            0.05263157894736842
          ]
        },
        "nohall": {
          "mean": 0.0,
          "variance": 0.0,
          "std": 0.0,
          "values": [
            0.0,
            0.0,
            0.0,
            0.0,
            0.0
          ]
        },
        "storyscore": {
          "mean": 0.5129552624995934,
          "variance": 1.6689227603303262e-05,
          "std": 0.004085245109329826,
          "values": [
            0.5069468360513312,
            0.5138869674423892,
            0.5137115369902716,
            0.5182684659957886,
            0.5119625060181868
          ]
        }
      },
      "baseline": {
        "n": 5,
        "bertscore": {
          "mean": 0.8240514516830444,
          "variance": 6.767084468606299e-06,
          "std": 0.0026013620410481695,
          "values": [
            0.8264176845550537,
            0.8199033737182617,
            0.8235986232757568,
            0.826052188873291,
            0.8242853879928589
          ]
        },
        "lexical_recall": {
          "mean": 0.027565383140357013,
          "variance": 1.8432100468279142e-05,
          "std": 0.004293262217507701,
          "values": [
            0.025069637883008356,
            0.022653721682847898,
            0.026845637583892617,
            0.033846153846153845,
            0.029411764705882353
          ]
        },
        "title_cov": {
          "mean": 0.0,
          "variance": 0.0,
          "std": 0.0,
          "values": [
            0.0,
            0.0,
            0.0,
            0.0,
            0.0
          ]
        },
        "noloop": {
          "mean": 0.9672744293476605,
          "variance": 0.0001775158123285638,
          "std": 0.013323506007375228,
          "values": [
            0.9574468085106383,
            0.9761904761904762,
            0.9487179487179487,
            0.9767441860465116,
            0.9772727272727273
          ]
        },
        "ctx_recall": {
          "mean": 0.027565383140357013,
          "variance": 1.8432100468279142e-05,
          "std": 0.004293262217507701,
          "values": [
            0.025069637883008356,
            0.022653721682847898,
            0.026845637583892617,
            0.033846153846153845,
            0.029411764705882353
          ]
        },
        "nohall": {
          "mean": 0.0,
          "variance": 0.0,
          "std": 0.0,
          "values": [
            0.0,
            0.0,
            0.0,
            0.0,
            0.0
          ]
        },
        "storyscore": {
          "mean": 0.5054570242659694,
          "variance": 8.720382721946846e-06,
          "std": 0.0029530294143382397,
          "values": [
            0.5058784658862355,
            0.5010035129040962,
            0.5048974289990111,
            0.5091697748624361,
            0.5063359386780683
          ]
        }
      }
    },
    "bertha_von_suttner": {
      "event_driven": {
        "n": 5,
        "bertscore": {
          "mean": 0.8041733264923095,
          "variance": 4.3415852754691285e-06,
          "std": 0.0020836471091499943,
          "values": [
            0.8020634055137634,
            0.803887128829956,
            0.8076447248458862,
            0.8039550185203552,
            0.8033163547515869
          ]
        },
        "lexical_recall": {
          "mean": 0.04533117479339229,
          "variance": 4.440180254963592e-06,
          "std": 0.002107173522746428,
          "values": [
            0.045307443365695796,
            0.0473186119873817,
            0.045871559633027525,
            0.046357615894039736,
            0.04180064308681672
          ]
        },
        "title_cov": {
          "mean": 0.0,
          "variance": 0.0,
          "std": 0.0,
          "values": [
            0.0,
            0.0,
            0.0,
            0.0,
            0.0
          ]
        },
        "noloop": {
          "mean": 0.9025858250276855,
          "variance": 0.001500763573862933,
          "std": 0.038739689904062645,
          "values": [
            0.85,
            0.95,
            0.9069767441860466,
            0.925,
            0.8809523809523809
          ]
        },
        "ctx_recall": {
          "mean": 0.04533117479339229,
          "variance": 4.440180254963592e-06,
          "std": 0.002107173522746428,
          "values": [
            0.045307443365695796,
            0.0473186119873817,
            0.045871559633027525,
            0.046357615894039736,
            0.04180064308681672
          ]
        },
        "nohall": {
          "mean": 0.0,
          "variance": 0.0,
          "std": 0.0,
          "values": [
            0.0,
            0.0,
            0.0,
            0.0,
            0.0
          ]
        },
        "storyscore": {
          "mean": 0.5006364658127427,
          "variance": 2.77243732732416e-06,
          "std": 0.0016650637607383567,
          "values": [
            0.49936102065453636,
            0.5012597220929264,
            0.5029354587607427,
            0.500916057469829,
            0.4987100700856788
          ]
        }
      },
      "baseline": {
        "n": 5,
        "bertscore": {
          "mean": 0.7972181797027588,
          "variance": 5.85870790210663e-06,
          "std": 0.002420476792309034,
          "values": [
            0.7953159809112549,
            0.8003143072128296,
            0.7973437309265137,
            0.7943969368934631,
            0.7987199425697327
          ]
        },
        "lexical_recall": {
          "mean": 0.04237521155135454,
          "variance": 2.5546731387671536e-06,
          "std": 0.001598334489012595,
          "values": [
            0.043478260869565216,
            0.040229885057471264,
            0.04143646408839779,
            0.042483660130718956,
            0.04424778761061947
          ]
        },
        "title_cov": {
          "mean": 0.0,
          "variance": 0.0,
          "std": 0.0,
          "values": [
            0.0,
            0.0,
            0.0,
            0.0,
            0.0
          ]
        },
        "noloop": {
          "mean": 0.9496753246753247,
          "variance": 0.0007106664980041603,
          "std": 0.026658328867432038,
          "values": [
            0.9761904761904762,
            0.9545454545454546,
            0.9583333333333334,
            0.9047619047619048,
            0.9545454545454546
          ]
        },
        "ctx_recall": {
          "mean": 0.04237521155135454,
          "variance": 2.5546731387671536e-06,
          "std": 0.001598334489012595,
          "values": [
            0.043478260869565216,
            0.040229885057471264,
            0.04143646408839779,
            0.042483660130718956,
            0.04424778761061947
          ]
        },
        "nohall": {
          "mean": 0.0,
          "variance": 0.0,
          "std": 0.0,
          "values": [
            0.0,
            0.0,
            0.0,
            0.0,
            0.0
          ]
        },
        "storyscore": {
          "mean": 0.49528099244219703,
          "variance": 1.755633075126166e-06,
          "std": 0.0013250030472139172,
          "values": [
            0.494580892894579,
            0.49628053835068625,
            0.4949808241912673,
            0.4936316261883654,
            0.49693108058608737
          ]
        }
      }
    },
    "charlie_chaplin": {
      "event_driven": {
        "n": 5,
        "bertscore": {
          "mean": 0.8424735069274902,
          "variance": 3.5529477298013035e-06,
          "std": 0.001884926452093371,
          "values": [
            0.8432237505912781,
            0.8404056429862976,
            0.8444317579269409,
            0.8437861204147339,
            0.8405202627182007
          ]
        },
        "lexical_recall": {
          "mean": 0.2503069738209621,
          "variance": 0.0004446037310374965,
          "std": 0.021085628542623445,
          "values": [
            0.22,
            0.24709302325581395,
            0.2791411042944785,
            0.2545454545454545,
            0.25075528700906347
          ]
        },
        "title_cov": {
          "mean": 0.0,
          "variance": 0.0,
          "std": 0.0,
          "values": [
            0.0,
            0.0,
            0.0,
            0.0,
            0.0
          ]
        },
        "noloop": {
          "mean": 0.9761904066232366,
          "variance": 3.335230641951596e-06,
          "std": 0.001826261383797948,
          "values": [
            0.9736842105263158,
            0.9787234042553191,
            0.9761904761904762,
            0.975609756097561,
            0.9767441860465116
          ]
        },
        "ctx_recall": {
          "mean": 0.2503069738209621,
          "variance": 0.0004446037310374965,
          "std": 0.021085628542623445,
          "values": [
            0.22,
            0.24709302325581395,
            0.2791411042944785,
            0.2545454545454545,
            0.25075528700906347
          ]
        },
        "nohall": {
          "mean": 0.265982905982906,
          "variance": 0.0031362407772664216,
          "std": 0.05600214975575868,
          "values": [
            0.33333333333333337,
            0.2666666666666667,
            0.2222222222222222,
            0.19999999999999996,
            0.3076923076923077
          ]
        },
        "storyscore": {
          "mean": 0.605606893684879,
          "variance": 7.782294023455153e-05,
          "std": 0.008821731135925166,
          "values": [
            0.5939342503547668,
            0.603080595094104,
            0.618315496473956,
            0.6080898540670221,
            0.6046142724345458
          ]
        }
      },
      "baseline": {
        "n": 5,
        "bertscore": {
          "mean": 0.8502910137176514,
          "variance": 6.132304299910629e-06,
          "std": 0.0024763489858884245,
          "values": [
            0.8503091931343079,
            0.8466016054153442,
            0.8521965146064758,
            0.8528661131858826,
            0.8494816422462463
          ]
        },
        "lexical_recall": {
          "mean": 0.2300354781231822,
          "variance": 0.00037483320297326686,
          "std": 0.01936060957132463,
          "values": [
            0.21621621621621623,
            0.22038567493112948,
            0.21813031161473087,
            0.2626865671641791,
            0.23275862068965517
          ]
        },
        "title_cov": {
          "mean": 0.0,
          "variance": 0.0,
          "std": 0.0,
          "values": [
            0.0,
            0.0,
            0.0,
            0.0,
            0.0
          ]
        },
        "noloop": {
          "mean": 0.9645981033144082,
          "variance": 0.000146778019430764,
          "std": 0.012115197870062377,
          "values": [
            0.9534883720930233,
            0.9782608695652174,
            0.9574468085106383,
            0.9772727272727273,
            0.9565217391304348
          ]
        },
        "ctx_recall": {
          "mean": 0.2300354781231822,
          "variance": 0.00037483320297326686,
          "std": 0.01936060957132463,
          "values": [
            0.21621621621621623,
            0.22038567493112948,
            0.21813031161473087,
            0.2626865671641791,
            0.23275862068965517
          ]
        },
        "nohall": {
          "mean": 0.3474358974358974,
          "variance": 0.025981329415395348,
          "std": 0.1611872495434901,
          "values": [
            0.5714285714285714,
            0.15384615384615385,
            0.4285714285714286,
            0.33333333333333337,
            0.25
          ]
        },
        "storyscore": {
          "mean": 0.6021887994798637,
          "variance": 7.352589810164359e-05,
          "std": 0.008574724374674884,
          "values": [
            0.5966720023670712,
            0.5961152332216583,
            0.5985700334097779,
            0.6167942947772012,
            0.6027924336236098
          ]
        }
      }
    },
    "cristiano_ronaldo": {
      "event_driven": {
        "n": 5,
        "bertscore": {
          "mean": 0.8465914845466613,
          "variance": 2.5047648643905517e-05,
          "std": 0.005004762596158335,
          "values": [
            0.8397027850151062,
            0.8436976671218872,
            0.8485294580459595,
            0.8527316451072693,
            0.8482958674430847
          ]
        },
        "lexical_recall": {
          "mean": 0.3019487607549081,
          "variance": 0.00013353175423426667,
          "std": 0.011555594066696297,
          "values": [
            0.2968299711815562,
            0.29393939393939394,
            0.3076923076923077,
            0.2917933130699088,
            0.3194888178913738
          ]
        },
        "title_cov": {
          "mean": 0.0,
          "variance": 0.0,
          "std": 0.0,
          "values": [
            0.0,
            0.0,
            0.0,
            0.0,
            0.0
          ]
        },
        "noloop": {
          "mean": 0.9459523809523811,
          "variance": 0.0005316515495086932,
          "std": 0.023057570329692006,
          "values": [
            0.9555555555555556,
            0.9555555555555556,
            0.9583333333333334,
            0.9555555555555556,
            0.9047619047619048
          ]
        },
        "ctx_recall": {
          "mean": 0.3019487607549081,
          "variance": 0.00013353175423426667,
          "std": 0.011555594066696297,
          "values": [
            0.2968299711815562,
            0.29393939393939394,
            0.3076923076923077,
            0.2917933130699088,
            0.3194888178913738
          ]
        },
        "nohall": {
          "mean": 0.37429813664596273,
          "variance": 0.004028552482114457,
          "std": 0.06347087900852215,
          "values": [
            0.35,
            0.38095238095238093,
            0.36,
            0.47619047619047616,
            0.30434782608695654
          ]
        },
        "storyscore": {
          "mean": 0.62873439502996,
          "variance": 3.483533631486552e-05,
          "std": 0.0059021467547719884,
          "values": [
            0.6225536594816862,
            0.6237943578488898,
            0.6321945979044987,
            0.628356312292325,
            0.6367730476224003
          ]
        }
      },
      "baseline": {
        "n": 5,
        "bertscore": {
          "mean": 0.8370577573776246,
          "variance": 1.1432577839798342e-05,
          "std": 0.0033812095232029532,
          "values": [
            0.8418748378753662,
            0.8357911109924316,
            0.8391517400741577,
            0.8336845636367798,
            0.8347865343093872
          ]
        },
        "lexical_recall": {
          "mean": 0.22158776358986404,
          "variance": 0.000586096977102154,
          "std": 0.0242094398345388,
          "values": [
            0.2551928783382789,
            0.1885245901639344,
            0.2292817679558011,
            0.21367521367521367,
            0.22126436781609196
          ]
        },
        "title_cov": {
          "mean": 0.0,
          "variance": 0.0,
          "std": 0.0,
          "values": [
            0.0,
            0.0,
            0.0,
            0.0,
            0.0
          ]
        },
        "noloop": {
          "mean": 0.9581179138321996,
          "variance": 2.232544567335526e-06,
          "std": 0.0014941701935641488,
          "values": [
            0.9555555555555556,
            0.9591836734693877,
            0.9591836734693877,
            0.9583333333333334,
            0.9583333333333334
          ]
        },
        "ctx_recall": {
          "mean": 0.22158776358986404,
          "variance": 0.000586096977102154,
          "std": 0.0242094398345388,
          "values": [
            0.2551928783382789,
            0.1885245901639344,
            0.2292817679558011,
            0.21367521367521367,
            0.22126436781609196
          ]
        },
        "nohall": {
          "mean": 0.37872315592903827,
          "variance": 0.003839567553600963,
          "std": 0.06196424415419721,
          "values": [
            0.4285714285714286,
            0.2857142857142857,
            0.38888888888888884,
            0.3529411764705882,
            0.4375
          ]
        },
        "storyscore": {
          "mean": 0.5908697598625203,
          "variance": 0.00012756653297215512,
          "std": 0.011294535535919798,
          "values": [
            0.6072020540605313,
            0.5768845026610327,
            0.5952037512268151,
            0.5856808236521533,
            0.5893776677120691
          ]
        }
      }
    },
    "fairuz": {
      "event_driven": {
        "n": 5,
        "bertscore": {
          "mean": 0.8290809392929077,
          "variance": 5.848635623806331e-06,
          "std": 0.002418395257977143,
          "values": [
            0.8303624987602234,
            0.8326111435890198,
            0.8271391987800598,
            0.8268089890480042,
            0.8284828662872314
          ]
        },
        "lexical_recall": {
          "mean": 0.10065707120485916,
          "variance": 6.275447243159576e-05,
          "std": 0.007921772051226655,
          "values": [
            0.10963455149501661,
            0.10434782608695652,
            0.09821428571428571,
            0.08852459016393442,
            0.10256410256410256
          ]
        },
        "title_cov": {
          "mean": 0.0,
          "variance": 0.0,
          "std": 0.0,
          "values": [
            0.0,
            0.0,
            0.0,
            0.0,
            0.0
          ]
        },
        "noloop": {
          "mean": 0.9544666100792625,
          "variance": 0.0002613365578667355,
          "std": 0.016165907270139078,
          "values": [
            0.975609756097561,
            0.9574468085106383,
            0.9555555555555556,
            0.9302325581395349,
            0.9534883720930233
          ]
        },
        "ctx_recall": {
          "mean": 0.10065707120485916,
          "variance": 6.275447243159576e-05,
          "std": 0.007921772051226655,
          "values": [
            0.10963455149501661,
            0.10434782608695652,
            0.09821428571428571,
            0.08852459016393442,
            0.10256410256410256
          ]
        },
        "nohall": {
          "mean": 0.10207070707070709,
          "variance": 0.0002718600142842564,
          "std": 0.01648817801590753,
          "values": [
            0.11111111111111116,
            0.09090909090909094,
            0.08333333333333337,
            0.09999999999999998,
            0.125
          ]
        },
        "storyscore": {
          "mean": 0.5377113920576883,
          "variance": 1.883039222710805e-05,
          "std": 0.0043393999846877505,
          "values": [
            0.5420713198541407,
            0.5413058165881944,
            0.5355692335537502,
            0.5314952294943762,
            0.5381153607979798
          ]
        }
      },
      "baseline": {
        "n": 5,
        "bertscore": {
          "mean": 0.828692352771759,
          "variance": 1.2916925814465686e-05,
          "std": 0.003594012495034719,
          "values": [
            0.8232361078262329,
            0.8271220922470093,
            0.8322852849960327,
            0.8298490047454834,
            0.8309692740440369
          ]
        },
        "lexical_recall": {
          "mean": 0.09805678508601652,
          "variance": 0.00012514443626664308,
          "std": 0.011186797408849553,
          "values": [
            0.08241758241758242,
            0.09785932721712538,
            0.09742120343839542,
            0.09855072463768116,
            0.11403508771929824
          ]
        },
        "title_cov": {
          "mean": 0.0,
          "variance": 0.0,
          "std": 0.0,
          "values": [
            0.0,
            0.0,
            0.0,
            0.0,
            0.0
          ]
        },
        "noloop": {
          "mean": 0.9660950338077997,
          "variance": 0.00013407525625960579,
          "std": 0.011579087021851325,
          "values": [
            0.9615384615384616,
            0.9545454545454546,
            0.9791666666666666,
            0.9574468085106383,
            0.9777777777777777
          ]
        },
        "ctx_recall": {
          "mean": 0.09805678508601652,
          "variance": 0.00012514443626664308,
          "std": 0.011186797408849553,
          "values": [
            0.08241758241758242,
            0.09785932721712538,
            0.09742120343839542,
            0.09855072463768116,
            0.11403508771929824
          ]
        },
        "nohall": {
          "mean": 0.10493506493506495,
          "variance": 0.0004700624051273408,
          "std": 0.021680922607844454,
          "values": [
            0.09090909090909094,
            0.09090909090909094,
            0.1428571428571429,
            0.09999999999999998,
            0.09999999999999998
          ]
        },
        "storyscore": {
          "mean": 0.536438125697462,
          "variance": 3.911045497709944e-05,
          "std": 0.006253835221454067,
          "values": [
            0.5269086976627727,
            0.5354169862350557,
            0.5383396523729778,
            0.5373296927023625,
            0.5441955995141414
          ]
        }
      }
    },
    "frida_kahlo": {
      "event_driven": {
        "n": 5,
        "bertscore": {
          "mean": 0.8383361101150513,
          "variance": 7.937608685892883e-06,
          "std": 0.0028173762059570395,
          "values": [
            0.8341596126556396,
            0.8413556218147278,
            0.8397547602653503,
            0.8394588828086853,
            0.8369516730308533
          ]
        },
        "lexical_recall": {
          "mean": 0.23061759956733008,
          "variance": 0.00023771442321751903,
          "std": 0.015417990245733036,
          "values": [
            0.22128851540616246,
            0.2558139534883721,
            0.23125,
            0.22916666666666666,
            0.2155688622754491
          ]
        },
        "title_cov": {
          "mean": 0.0,
          "variance": 0.0,
          "std": 0.0,
          "values": [
            0.0,
            0.0,
            0.0,
            0.0,
            0.0
          ]
        },
        "noloop": {
          "mean": 0.9644643109874039,
          "variance": 0.0001212877173951205,
          "std": 0.011013070298291957,
          "values": [
            0.9574468085106383,
            0.9574468085106383,
            0.975609756097561,
            0.9545454545454546,
            0.9772727272727273
          ]
        },
        "ctx_recall": {
          "mean": 0.23061759956733008,
          "variance": 0.00023771442321751903,
          "std": 0.015417990245733036,
          "values": [
            0.22128851540616246,
            0.2558139534883721,
            0.23125,
            0.22916666666666666,
            0.2155688622754491
          ]
        },
        "nohall": {
          "mean": 0.19762626262626265,
          "variance": 0.007622870115294358,
          "std": 0.08730904944674611,
          "values": [
            0.25,
            0.30000000000000004,
            0.09090909090909094,
            0.125,
            0.2222222222222222
          ]
        },
        "storyscore": {
          "mean": 0.5952487058959628,
          "variance": 5.7109330704499916e-05,
          "std": 0.007557071569364678,
          "values": [
            0.5890111737558488,
            0.6071389544841855,
            0.5963528561592102,
            0.5953419963518778,
            0.5883985487286916
          ]
        }
      },
      "baseline": {
        "n": 5,
        "bertscore": {
          "mean": 0.8393570184707642,
          "variance": 1.0510852519018954e-05,
          "std": 0.003242044496767272,
          "values": [
            0.8351048827171326,
            0.8422836661338806,
            0.8367767930030823,
            0.8405640125274658,
            0.8420557379722595
          ]
        },
        "lexical_recall": {
          "mean": 0.2252364582654034,
          "variance": 0.0001874683275641505,
          "std": 0.013691907374947819,
          "values": [
            0.24,
            0.23692307692307693,
            0.22028985507246376,
            0.20612813370473537,
            0.22284122562674094
          ]
        },
        "title_cov": {
          "mean": 0.0,
          "variance": 0.0,
          "std": 0.0,
          "values": [
            0.0,
            0.0,
            0.0,
            0.0,
            0.0
          ]
        },
        "noloop": {
          "mean": 0.9691486643437862,
          "variance": 0.0001638651028029694,
          "std": 0.01280098054068396,
          "values": [
            0.9761904761904762,
            0.9512195121951219,
            0.9791666666666666,
            0.96,
            0.9791666666666666
          ]
        },
        "ctx_recall": {
          "mean": 0.2252364582654034,
          "variance": 0.0001874683275641505,
          "std": 0.013691907374947819,
          "values": [
            0.24,
            0.23692307692307693,
            0.22028985507246376,
            0.20612813370473537,
            0.22284122562674094
          ]
        },
        "nohall": {
          "mean": 0.573015873015873,
          "variance": 0.01380700428319476,
          "std": 0.11750320967188412,
          "values": [
            0.6666666666666667,
            0.4285714285714286,
            0.7142857142857143,
            0.5,
            0.5555555555555556
          ]
        },
        "storyscore": {
          "mean": 0.5937087943886199,
          "variance": 2.833824185915997e-05,
          "std": 0.005323367529971979,
          "values": [
            0.5970629296302795,
            0.6001394304495591,
            0.5901820178308349,
            0.5867896609983737,
            0.5943699330340521
          ]
        }
      }
    },
    "johnny_depp": {
      "event_driven": {
        "n": 5,
        "bertscore": {
          "mean": 0.8199096918106079,
          "variance": 0.00016674252096748887,
          "std": 0.0129128819776024,
          "values": [
            0.829131543636322,
            0.818971574306488,
            0.7994894981384277,
            0.8327016234397888,
            0.8192542195320129
          ]
        },
        "lexical_recall": {
          "mean": 0.19366134533082915,
          "variance": 0.001161494302682492,
          "std": 0.03408070279032538,
          "values": [
            0.1977077363896848,
            0.22916666666666666,
            0.1407766990291262,
            0.21587301587301588,
            0.18478260869565216
          ]
        },
        "title_cov": {
          "mean": 0.0,
          "variance": 0.0,
          "std": 0.0,
          "values": [
            0.0,
            0.0,
            0.0,
            0.0,
            0.0
          ]
        },
        "noloop": {
          "mean": 0.9454385773179602,
          "variance": 9.114605175870614e-05,
          "std": 0.00954704413725558,
          "values": [
            0.9545454545454546,
            0.9523809523809523,
            0.935483870967742,
            0.95,
            0.9347826086956522
          ]
        },
        "ctx_recall": {
          "mean": 0.19366134533082915,
          "variance": 0.001161494302682492,
          "std": 0.03408070279032538,
          "values": [
            0.1977077363896848,
            0.22916666666666666,
            0.1407766990291262,
            0.21587301587301588,
            0.18478260869565216
          ]
        },
        "nohall": {
          "mean": 0.18715728715728716,
          "variance": 0.00516811070923625,
          "std": 0.07188957302165766,
          "values": [
            0.18181818181818177,
            0.1428571428571429,
            0.11111111111111116,
            0.30000000000000004,
            0.19999999999999996
          ]
        },
        "storyscore": {
          "mean": 0.5694103532186964,
          "variance": 0.00041073100139151354,
          "std": 0.020266499485394943,
          "values": [
            0.5765620207376672,
            0.5830496112505594,
            0.5360043784947071,
            0.5859701804130797,
            0.5654655751974687
          ]
        }
      },
      "baseline": {
        "n": 5,
        "bertscore": {
          "mean": 0.8258397579193115,
          "variance": 2.864360178023162e-05,
          "std": 0.005351971765642231,
          "values": [
            0.8205517530441284,
            0.831994354724884,
            0.8261778950691223,
            0.8203439116477966,
            0.8301308751106262
          ]
        },
        "lexical_recall": {
          "mean": 0.19128090085247135,
          "variance": 0.00042541828466698996,
          "std": 0.02062567052648204,
          "values": [
            0.17559523809523808,
            0.21700879765395895,
            0.1694915254237288,
            0.18597560975609756,
            0.20833333333333334
          ]
        },
        "title_cov": {
          "mean": 0.0,
          "variance": 0.0,
          "std": 0.0,
          "values": [
            0.0,
            0.0,
            0.0,
            0.0,
            0.0
          ]
        },
        "noloop": {
          "mean": 0.9610177865612648,
          "variance": 0.00010472702623415739,
          "std": 0.010233622341778955,
          "values": [
            0.9565217391304348,
            0.9565217391304348,
            0.9583333333333334,
            0.9545454545454546,
            0.9791666666666666
          ]
        },
        "ctx_recall": {
          "mean": 0.19128090085247135,
          "variance": 0.00042541828466698996,
          "std": 0.02062567052648204,
          "values": [
            0.17559523809523808,
            0.21700879765395895,
            0.1694915254237288,
            0.18597560975609756,
            0.20833333333333334
          ]
        },
        "nohall": {
          "mean": 0.34500000000000003,
          "variance": 0.009499999999999998,
          "std": 0.09746794344808962,
          "values": [
            0.5,
            0.375,
            0.30000000000000004,
            0.25,
            0.30000000000000004
          ]
        },
        "storyscore": {
          "mean": 0.5720162150925755,
          "variance": 0.00011872909567871772,
          "std": 0.010896288160594769,
          "values": [
            0.5625691470645723,
            0.586000131896514,
            0.563503347210965,
            0.5665965908911169,
            0.5814118583997091
          ]
        }
      }
    },
    "klaus_nomi": {
      "event_driven": {
        "n": 5,
        "bertscore": {
          "mean": 0.8413056612014771,
          "variance": 1.0651300249620023e-05,
          "std": 0.0032636329832902507,
          "values": [
            0.838516116142273,
            0.8464708924293518,
            0.8402948379516602,
            0.8423826098442078,
            0.8388638496398926
          ]
        },
        "lexical_recall": {
          "mean": 0.07975218545782434,
          "variance": 3.5371390865816205e-05,
          "std": 0.00594738521249601,
          "values": [
            0.08206686930091185,
            0.08823529411764706,
            0.07987220447284345,
            0.07580174927113703,
            0.07278481012658228
          ]
        },
        "title_cov": {
          "mean": 0.0,
          "variance": 0.0,
          "std": 0.0,
          "values": [
            0.0,
            0.0,
            0.0,
            0.0,
            0.0
          ]
        },
        "noloop": {
          "mean": 0.9673738630765932,
          "variance": 0.00016272998049842555,
          "std": 0.012756566171914193,
          "values": [
            0.9534883720930233,
            0.9772727272727273,
            0.9743589743589743,
            0.9782608695652174,
            0.9534883720930233
          ]
        },
        "ctx_recall": {
          "mean": 0.07975218545782434,
          "variance": 3.5371390865816205e-05,
          "std": 0.00594738521249601,
          "values": [
            0.08206686930091185,
            0.08823529411764706,
            0.07987220447284345,
            0.07580174927113703,
            0.07278481012658228
          ]
        },
        "nohall": {
          "mean": 0.39,
          "variance": 0.015187499999999994,
          "std": 0.12323757543866236,
          "values": [
            0.6,
            0.375,
            0.30000000000000004,
            0.30000000000000004,
            0.375
          ]
        },
        "storyscore": {
          "mean": 0.536684270904016,
          "variance": 1.5493600902618875e-05,
          "std": 0.003936191166930142,
          "values": [
            0.5359364174057285,
            0.5431766531046699,
            0.5361257845601334,
            0.5357502656149795,
            0.5324322338345685
          ]
        }
      },
      "baseline": {
        "n": 5,
        "bertscore": {
          "mean": 0.8419474601745606,
          "variance": 2.1549173213131213e-05,
          "std": 0.004642108703286817,
          "values": [
            0.8370590209960938,
            0.8387348651885986,
            0.8418885469436646,
            0.8490838408470154,
            0.8429710268974304
          ]
        },
        "lexical_recall": {
          "mean": 0.08040848398269244,
          "variance": 0.0002667311263486624,
          "std": 0.016331905165921777,
          "values": [
            0.07323943661971831,
            0.06593406593406594,
            0.0670391061452514,
            0.10059171597633136,
            0.09523809523809523
          ]
        },
        "title_cov": {
          "mean": 0.0,
          "variance": 0.0,
          "std": 0.0,
          "values": [
            0.0,
            0.0,
            0.0,
            0.0,
            0.0
          ]
        },
        "noloop": {
          "mean": 0.9573352652809506,
          "variance": 0.0002514119246142078,
          "std": 0.015855974413898622,
          "values": [
            0.9565217391304348,
            0.9795918367346939,
            0.9583333333333334,
            0.9347826086956522,
            0.9574468085106383
          ]
        },
        "ctx_recall": {
          "mean": 0.08040848398269244,
          "variance": 0.0002667311263486624,
          "std": 0.016331905165921777,
          "values": [
            0.07323943661971831,
            0.06593406593406594,
            0.0670391061452514,
            0.10059171597633136,
            0.09523809523809523
          ]
        },
        "nohall": {
          "mean": 0.24285714285714283,
          "variance": 0.0059369202226345116,
          "std": 0.07705141285294197,
          "values": [
            0.2727272727272727,
            0.2142857142857143,
            0.18181818181818177,
            0.36363636363636365,
            0.18181818181818177
          ]
        },
        "storyscore": {
          "mean": 0.5373318696978133,
          "variance": 7.942042473977576e-05,
          "std": 0.008911813773849617,
          "values": [
            0.5315311872455436,
            0.5296145454867855,
            0.5319487706242992,
            0.5496869908987417,
            0.5438778542336963
          ]
        }
      }
    },
    "leonardo_da_vinci": {
      "event_driven": {
        "n": 5,
        "bertscore": {
          "mean": 0.8333849549293518,
          "variance": 1.0554216666136539e-05,
          "std": 0.0032487253910012982,
          "values": [
            0.8346225619316101,
            0.837674081325531,
            0.8287023305892944,
            0.8329111337661743,
            0.8330146670341492
          ]
        },
        "lexical_recall": {
          "mean": 0.20677836941408131,
          "variance": 0.0001921506381870645,
          "std": 0.013861841082160209,
          "values": [
            0.19293478260869565,
            0.20402298850574713,
            0.2,
            0.22965116279069767,
            0.20728291316526612
          ]
        },
        "title_cov": {
          "mean": 0.0,
          "variance": 0.0,
          "std": 0.0,
          "values": [
            0.0,
            0.0,
            0.0,
            0.0,
            0.0
          ]
        },
        "noloop": {
          "mean": 0.9729104711713408,
          "variance": 9.46592121294857e-05,
          "std": 0.009729296589655684,
          "values": [
            0.9782608695652174,
            0.9772727272727273,
            0.9761904761904762,
            0.9772727272727273,
            0.9555555555555556
          ]
        },
        "ctx_recall": {
          "mean": 0.20677836941408131,
          "variance": 0.0001921506381870645,
          "std": 0.013861841082160209,
          "values": [
            0.19293478260869565,
            0.20402298850574713,
            0.2,
            0.22965116279069767,
            0.20728291316526612
          ]
        },
        "nohall": {
          "mean": 0.28024595803233576,
          "variance": 0.0030529770553717217,
          "std": 0.05525375150495866,
          "values": [
            0.2777777777777778,
            0.375,
            0.23529411764705888,
            0.25,
            0.26315789473684215
          ]
        },
        "storyscore": {
          "mean": 0.5827423207232436,
          "variance": 3.355542258721271e-05,
          "std": 0.00579270425511373,
          "values": [
            0.5779474502024442,
            0.5842136441976175,
            0.5772213983535767,
            0.5916071453759837,
            0.5827219654865959
          ]
        }
      },
      "baseline": {
        "n": 5,
        "bertscore": {
          "mean": 0.8241169333457947,
          "variance": 3.3479125594482186e-06,
          "std": 0.001829730187609151,
          "values": [
            0.8244052529335022,
            0.8261044025421143,
            0.8249648213386536,
            0.8211838006973267,
            0.8239263892173767
          ]
        },
        "lexical_recall": {
          "mean": 0.16587497762336914,
          "variance": 9.19803934600203e-05,
          "std": 0.009590640930616698,
          "values": [
            0.15013404825737264,
            0.1662269129287599,
            0.17344173441734417,
            0.17379679144385027,
            0.1657754010695187
          ]
        },
        "title_cov": {
          "mean": 0.0,
          "variance": 0.0,
          "std": 0.0,
          "values": [
            0.0,
            0.0,
            0.0,
            0.0,
            0.0
          ]
        },
        "noloop": {
          "mean": 0.9788692943328201,
          "variance": 9.257189105087382e-07,
          "std": 0.0009621428742701046,
          "values": [
            0.9795918367346939,
            0.9795918367346939,
            0.9772727272727273,
            0.9787234042553191,
            0.9791666666666666
          ]
        },
        "ctx_recall": {
          "mean": 0.16587497762336914,
          "variance": 9.19803934600203e-05,
          "std": 0.009590640930616698,
          "values": [
            0.15013404825737264,
            0.1662269129287599,
            0.17344173441734417,
            0.17379679144385027,
            0.1657754010695187
          ]
        },
        "nohall": {
          "mean": 0.31619047619047624,
          "variance": 0.006911564625850346,
          "std": 0.08313582035350554,
          "values": [
            0.33333333333333337,
            0.33333333333333337,
            0.19999999999999996,
            0.4285714285714286,
            0.2857142857142857
          ]
        },
        "storyscore": {
          "mean": 0.5608201510568245,
          "variance": 1.3445317177385865e-05,
          "std": 0.003666785673772857,
          "values": [
            0.5546967710630504,
            0.5621534066967725,
            0.5643555865701297,
            0.5622289969959361,
            0.5606659939582335
          ]
        }
      }
    },
    "ludwig_van_beethoven": {
      "event_driven": {
        "n": 5,
        "bertscore": {
          "mean": 0.848998749256134,
          "variance": 1.189734925794994e-05,
          "std": 0.0034492534348681803,
          "values": [
            0.8535952568054199,
            0.8475437760353088,
            0.8504709601402283,
            0.8490933179855347,
            0.8442904353141785
          ]
        },
        "lexical_recall": {
          "mean": 0.2231212264495679,
          "variance": 0.00022718137547816285,
          "std": 0.015072537128106961,
          "values": [
            0.23734177215189872,
            0.21203438395415472,
            0.22699386503067484,
            0.2361111111111111,
            0.203125
          ]
        },
        "title_cov": {
          "mean": 0.0,
          "variance": 0.0,
          "std": 0.0,
          "values": [
            0.0,
            0.0,
            0.0,
            0.0,
            0.0
          ]
        },
        "noloop": {
          "mean": 0.9729079617593728,
          "variance": 0.00014806315984238543,
          "std": 0.012168120637238334,
          "values": [
            0.9512195121951219,
            0.9787234042553191,
            0.9767441860465116,
            0.9782608695652174,
            0.9795918367346939
          ]
        },
        "ctx_recall": {
          "mean": 0.2231212264495679,
          "variance": 0.00022718137547816285,
          "std": 0.015072537128106961,
          "values": [
            0.23734177215189872,
            0.21203438395415472,
            0.22699386503067484,
            0.2361111111111111,
            0.203125
          ]
        },
        "nohall": {
          "mean": 0.24136321195144722,
          "variance": 0.0014720212703817903,
          "std": 0.03836692938432512,
          "values": [
            0.25,
            0.25,
            0.2941176470588235,
            0.2222222222222222,
            0.19047619047619047
          ]
        },
        "storyscore": {
          "mean": 0.5986477401335076,
          "variance": 6.254096908286836e-05,
          "std": 0.007908284838248326,
          "values": [
            0.6070938629440115,
            0.5933400192028472,
            0.6010801220964069,
            0.6039004352357652,
            0.5878242611885071
          ]
        }
      },
      "baseline": {
        "n": 5,
        "bertscore": {
          "mean": 0.8437272548675537,
          "variance": 1.8489700832802215e-05,
          "std": 0.004299965212975823,
          "values": [
            0.8456336259841919,
            0.8502907752990723,
            0.8399222493171692,
            0.8404237031936646,
            0.8423659205436707
          ]
        },
        "lexical_recall": {
          "mean": 0.1764299772179132,
          "variance": 9.421729079111861e-05,
          "std": 0.00970655916332449,
          "values": [
            0.18037974683544303,
            0.1887905604719764,
            0.1710914454277286,
            0.1632047477744807,
            0.1786833855799373
          ]
        },
        "title_cov": {
          "mean": 0.0,
          "variance": 0.0,
          "std": 0.0,
          "values": [
            0.0,
            0.0,
            0.0,
            0.0,
            0.0
          ]
        },
        "noloop": {
          "mean": 0.9716936518149865,
          "variance": 0.0001476495716249468,
          "std": 0.012151114007569299,
          "values": [
            0.9761904761904762,
            0.9772727272727273,
            0.9782608695652174,
            0.9767441860465116,
            0.95
          ]
        },
        "ctx_recall": {
          "mean": 0.1764299772179132,
          "variance": 9.421729079111861e-05,
          "std": 0.00970655916332449,
          "values": [
            0.18037974683544303,
            0.1887905604719764,
            0.1710914454277286,
            0.1632047477744807,
            0.1786833855799373
          ]
        },
        "nohall": {
          "mean": 0.21111111111111108,
          "variance": 0.009587191358024693,
          "std": 0.09791420406674761,
          "values": [
            0.16666666666666663,
            0.16666666666666663,
            0.125,
            0.375,
            0.2222222222222222
          ]
        },
        "storyscore": {
          "mean": 0.5768083438076974,
          "variance": 3.968238649744264e-05,
          "std": 0.006299395724785247,
          "values": [
            0.5795320743246923,
            0.5856906893682339,
            0.5723899277613929,
            0.569536121025991,
            0.5768929065581773
          ]
        }
      }
    },
    "maria_callas": {
      "event_driven": {
        "n": 5,
        "bertscore": {
          "mean": 0.8420621871948242,
          "variance": 1.3174146002370434e-05,
          "std": 0.0036296206416608382,
          "values": [
            0.8391257524490356,
            0.8406997323036194,
            0.8388991951942444,
            0.8443143963813782,
            0.8472718596458435
          ]
        },
        "lexical_recall": {
          "mean": 0.1780476751692268,
          "variance": 0.00011040360336868358,
          "std": 0.010507311900228506,
          "values": [
            0.16417910447761194,
            0.18670886075949367,
            0.16932907348242812,
            0.1858108108108108,
            0.18421052631578946
          ]
        },
        "title_cov": {
          "mean": 0.0,
          "variance": 0.0,
          "std": 0.0,
          "values": [
            0.0,
            0.0,
            0.0,
            0.0,
            0.0
          ]
        },
        "noloop": {
          "mean": 0.9651190701190702,
          "variance": 0.00015637263130648137,
          "std": 0.012504904290176769,
          "values": [
            0.9545454545454546,
            0.975,
            0.9487179487179487,
            0.972972972972973,
            0.9743589743589743
          ]
        },
        "ctx_recall": {
          "mean": 0.1780476751692268,
          "variance": 0.00011040360336868358,
          "std": 0.010507311900228506,
          "values": [
            0.16417910447761194,
            0.18670886075949367,
            0.16932907348242812,
            0.1858108108108108,
            0.18421052631578946
          ]
        },
        "nohall": {
          "mean": 0.42272727272727273,
          "variance": 0.005865472910927455,
          "std": 0.07658637549151583,
          "values": [
            0.41666666666666663,
            0.33333333333333337,
            0.5,
            0.36363636363636365,
            0.5
          ]
        },
        "storyscore": {
          "mean": 0.5764563823845853,
          "variance": 3.513821151826616e-05,
          "std": 0.005927749279302065,
          "values": [
            0.5691470932604662,
            0.579103383685969,
            0.5710711465095178,
            0.5809129621531512,
            0.5820473263138218
          ]
        }
      },
      "baseline": {
        "n": 5,
        "bertscore": {
          "mean": 0.8340643882751465,
          "variance": 6.598751187425478e-06,
          "std": 0.002568803454417149,
          "values": [
            0.82963627576828,
            0.8361267447471619,
            0.8345426321029663,
            0.8344965577125549,
            0.8355197310447693
          ]
        },
        "lexical_recall": {
          "mean": 0.1303589673835574,
          "variance": 0.00017033969213745868,
          "std": 0.013051424908317816,
          "values": [
            0.12094395280235988,
            0.1174785100286533,
            0.12460063897763578,
            0.14411764705882352,
            0.14465408805031446
          ]
        },
        "title_cov": {
          "mean": 0.0,
          "variance": 0.0,
          "std": 0.0,
          "values": [
            0.0,
            0.0,
            0.0,
            0.0,
            0.0
          ]
        },
        "noloop": {
          "mean": 0.9729311058891319,
          "variance": 6.723085849350483e-05,
          "std": 0.00819944257212067,
          "values": [
            0.9777777777777777,
            0.9583333333333334,
            0.975609756097561,
            0.9767441860465116,
            0.9761904761904762
          ]
        },
        "ctx_recall": {
          "mean": 0.1303589673835574,
          "variance": 0.00017033969213745868,
          "std": 0.013051424908317816,
          "values": [
            0.12094395280235988,
            0.1174785100286533,
            0.12460063897763578,
            0.14411764705882352,
            0.14465408805031446
          ]
        },
        "nohall": {
          "mean": 0.28376068376068375,
          "variance": 0.0032653955730878835,
          "std": 0.0571436398305873,
          "values": [
            0.2222222222222222,
            0.33333333333333337,
            0.2222222222222222,
            0.33333333333333337,
            0.3076923076923077
          ]
        },
        "storyscore": {
          "mean": 0.5525822199185109,
          "variance": 3.432467863789414e-05,
          "std": 0.005858726707902848,
          "values": [
            0.5461593465819119,
            0.5486674508597584,
            0.5505658348528341,
            0.5583449934510624,
            0.5591734738469873
          ]
        }
      }
    },
    "marie_curie": {
      "event_driven": {
        "n": 5,
        "bertscore": {
          "mean": 0.836557412147522,
          "variance": 1.2817483884219881e-05,
          "std": 0.003580151377277207,
          "values": [
            0.8423387408256531,
            0.8344587683677673,
            0.8373247385025024,
            0.8331175446510315,
            0.8355472683906555
          ]
        },
        "lexical_recall": {
          "mean": 0.2609168142323931,
          "variance": 0.0001349703250952505,
          "std": 0.011617672963862019,
          "values": [
            0.275,
            0.24916943521594684,
            0.2689655172413793,
            0.24921135646687698,
            0.26223776223776224
          ]
        },
        "title_cov": {
          "mean": 0.0,
          "variance": 0.0,
          "std": 0.0,
          "values": [
            0.0,
            0.0,
            0.0,
            0.0,
            0.0
          ]
        },
        "noloop": {
          "mean": 0.9462897439677626,
          "variance": 0.0003774037210101879,
          "std": 0.019426881402072438,
          "values": [
            0.9705882352941176,
            0.9473684210526316,
            0.9444444444444444,
            0.9523809523809523,
            0.9166666666666666
          ]
        },
        "ctx_recall": {
          "mean": 0.2609168142323931,
          "variance": 0.0001349703250952505,
          "std": 0.011617672963862019,
          "values": [
            0.275,
            0.24916943521594684,
            0.2689655172413793,
            0.24921135646687698,
            0.26223776223776224
          ]
        },
        "nohall": {
          "mean": 0.32602397602397604,
          "variance": 0.005095638349884105,
          "std": 0.07138374009453487,
          "values": [
            0.36363636363636365,
            0.33333333333333337,
            0.23076923076923073,
            0.41666666666666663,
            0.2857142857142857
          ]
        },
        "storyscore": {
          "mean": 0.6063011729814705,
          "variance": 4.4351139963908386e-05,
          "std": 0.006659665154038031,
          "values": [
            0.6154032444953919,
            0.6003430351070391,
            0.6099810499980531,
            0.5995550693773697,
            0.6062234659294982
          ]
        }
      },
      "baseline": {
        "n": 5,
        "bertscore": {
          "mean": 0.8294546008110046,
          "variance": 5.331971824773518e-05,
          "std": 0.007302035212715369,
          "values": [
            0.8222384452819824,
            0.8403752446174622,
            0.8262629508972168,
            0.8252215385437012,
            0.8331748247146606
          ]
        },
        "lexical_recall": {
          "mean": 0.21952806521450324,
          "variance": 0.0010121127236087293,
          "std": 0.031813719109980355,
          "values": [
            0.1981981981981982,
            0.26755852842809363,
            0.1897590361445783,
            0.23512747875354106,
            0.20699708454810495
          ]
        },
        "title_cov": {
          "mean": 0.0,
          "variance": 0.0,
          "std": 0.0,
          "values": [
            0.0,
            0.0,
            0.0,
            0.0,
            0.0
          ]
        },
        "noloop": {
          "mean": 0.9535725772935075,
          "variance": 8.096351211321902e-06,
          "std": 0.0028454087951157213,
          "values": [
            0.9545454545454546,
            0.9487179487179487,
            0.9534883720930233,
            0.9555555555555556,
            0.9555555555555556
          ]
        },
        "ctx_recall": {
          "mean": 0.21952806521450324,
          "variance": 0.0010121127236087293,
          "std": 0.031813719109980355,
          "values": [
            0.1981981981981982,
            0.26755852842809363,
            0.1897590361445783,
            0.23512747875354106,
            0.20699708454810495
          ]
        },
        "nohall": {
          "mean": 0.4234343434343434,
          "variance": 0.00885695337210489,
          "std": 0.09411138811060482,
          "values": [
            0.5,
            0.5,
            0.4444444444444444,
            0.4,
            0.2727272727272727
          ]
        },
        "storyscore": {
          "mean": 0.585483986572404,
          "variance": 0.0002604296377258011,
          "std": 0.016137832497761313,
          "values": [
            0.5726223464484687,
            0.6112485581417147,
            0.5716613849961614,
            0.5891839146276372,
            0.5827037286480383
          ]
        }
      }
    },
    "miguel_de_cervantes": {
      "event_driven": {
        "n": 5,
        "bertscore": {
          "mean": 0.8262966394424438,
          "variance": 1.3039435032879966e-05,
          "std": 0.0036110157896193096,
          "values": [
            0.8275233507156372,
            0.8319836258888245,
            0.8233563303947449,
            0.8252511620521545,
            0.8233687281608582
          ]
        },
        "lexical_recall": {
          "mean": 0.18729588736259256,
          "variance": 0.00016775781855590173,
          "std": 0.012952135675474595,
          "values": [
            0.19637462235649547,
            0.20165745856353592,
            0.1853035143769968,
            0.18518518518518517,
            0.16795865633074936
          ]
        },
        "title_cov": {
          "mean": 0.0,
          "variance": 0.0,
          "std": 0.0,
          "values": [
            0.0,
            0.0,
            0.0,
            0.0,
            0.0
          ]
        },
        "noloop": {
          "mean": 0.9627342752634979,
          "variance": 0.00019001539260703957,
          "std": 0.013784607089323931,
          "values": [
            0.9512195121951219,
            0.9767441860465116,
            0.95,
            0.9574468085106383,
            0.9782608695652174
          ]
        },
        "ctx_recall": {
          "mean": 0.18729588736259256,
          "variance": 0.00016775781855590173,
          "std": 0.012952135675474595,
          "values": [
            0.19637462235649547,
            0.20165745856353592,
            0.1853035143769968,
            0.18518518518518517,
            0.16795865633074936
          ]
        },
        "nohall": {
          "mean": 0.4802020202020202,
          "variance": 0.012341393735333127,
          "std": 0.11109182569088118,
          "values": [
            0.5555555555555556,
            0.5454545454545454,
            0.30000000000000004,
            0.4444444444444444,
            0.5555555555555556
          ]
        },
        "storyscore": {
          "mean": 0.5706963386105033,
          "variance": 5.043468293414087e-05,
          "std": 0.0071017380220718416,
          "values": [
            0.5750638593719806,
            0.579853158958709,
            0.5681352039876456,
            0.5692247713053668,
            0.5612046994288147
          ]
        }
      },
      "baseline": {
        "n": 5,
        "bertscore": {
          "mean": 0.8219374060630799,
          "variance": 1.2219077693842451e-05,
          "std": 0.0034955797364446504,
          "values": [
            0.8185397386550903,
            0.8259218335151672,
            0.8199644088745117,
            0.8197492957115173,
            0.8255117535591125
          ]
        },
        "lexical_recall": {
          "mean": 0.16272437424830372,
          "variance": 0.00018865840340871016,
          "std": 0.013735297718240773,
          "values": [
            0.14357682619647355,
            0.1783783783783784,
            0.17222222222222222,
            0.1638888888888889,
            0.15555555555555556
          ]
        },
        "title_cov": {
          "mean": 0.0,
          "variance": 0.0,
          "std": 0.0,
          "values": [
            0.0,
            0.0,
            0.0,
            0.0,
            0.0
          ]
        },
        "noloop": {
          "mean": 0.9779101020314368,
          "variance": 1.665641157935795e-06,
          "std": 0.0012905972097969974,
          "values": [
            0.98,
            0.9772727272727273,
            0.9772727272727273,
            0.9782608695652174,
            0.9767441860465116
          ]
        },
        "ctx_recall": {
          "mean": 0.16272437424830372,
          "variance": 0.00018865840340871016,
          "std": 0.013735297718240773,
          "values": [
            0.14357682619647355,
            0.1783783783783784,
            0.17222222222222222,
            0.1638888888888889,
            0.15555555555555556
          ]
        },
        "nohall": {
          "mean": 0.47018759018759015,
          "variance": 0.009360410953484543,
          "std": 0.09674921681070366,
          "values": [
            0.4444444444444444,
            0.36363636363636365,
            0.5714285714285714,
            0.4,
            0.5714285714285714
          ]
        },
        "storyscore": {
          "mean": 0.5582521933371694,
          "variance": 4.424638220110144e-05,
          "std": 0.006651795411849453,
          "values": [
            0.5485545736716436,
            0.5669044514604517,
            0.5608675342135959,
            0.557405132982466,
            0.5575292743576897
          ]
        }
      }
    },
    "pablo_picasso": {
      "event_driven": {
        "n": 5,
        "bertscore": {
          "mean": 0.8434529900550842,
          "variance": 8.376220817396529e-06,
          "std": 0.0028941701431319704,
          "values": [
            0.8415262699127197,
            0.84185391664505,
            0.8482745289802551,
            0.841550350189209,
            0.8440598845481873
          ]
        },
        "lexical_recall": {
          "mean": 0.1683930728055674,
          "variance": 7.550875137981957e-05,
          "std": 0.00868957716921943,
          "values": [
            0.15568862275449102,
            0.17699115044247787,
            0.1638418079096045,
            0.17065868263473055,
            0.17478510028653296
          ]
        },
        "title_cov": {
          "mean": 0.0,
          "variance": 0.0,
          "std": 0.0,
          "values": [
            0.0,
            0.0,
            0.0,
            0.0,
            0.0
          ]
        },
        "noloop": {
          "mean": 0.9726849310671353,
          "variance": 8.206027635296758e-05,
          "std": 0.009058712731562227,
          "values": [
            0.9761904761904762,
            0.9767441860465116,
            0.9777777777777777,
            0.9761904761904762,
            0.9565217391304348
          ]
        },
        "ctx_recall": {
          "mean": 0.1683930728055674,
          "variance": 7.550875137981957e-05,
          "std": 0.00868957716921943,
          "values": [
            0.15568862275449102,
            0.17699115044247787,
            0.1638418079096045,
            0.17065868263473055,
            0.17478510028653296
          ]
        },
        "nohall": {
          "mean": 0.07756056808688387,
          "variance": 0.0005692510306677295,
          "std": 0.023858982180045517,
          "values": [
            0.05555555555555558,
            0.10526315789473684,
            0.09999999999999998,
            0.0714285714285714,
            0.05555555555555558
          ]
        },
        "storyscore": {
          "mean": 0.5734290231552774,
          "variance": 1.3699260714191095e-05,
          "std": 0.003701251236297138,
          "values": [
            0.5671912110494282,
            0.5759088101640212,
            0.5745014405519949,
            0.5731936831674176,
            0.5763499708435256
          ]
        }
      },
      "baseline": {
        "n": 5,
        "bertscore": {
          "mean": 0.8409619212150574,
          "variance": 1.0604587825469024e-05,
          "std": 0.003256468612695204,
          "values": [
            0.8383198976516724,
            0.8430438041687012,
            0.8434414863586426,
            0.8434017300605774,
            0.8366026878356934
          ]
        },
        "lexical_recall": {
          "mean": 0.17196609808242508,
          "variance": 0.0004515369728583566,
          "std": 0.021249399352884227,
          "values": [
            0.14066496163682865,
            0.18435754189944134,
            0.19230769230769232,
            0.1826086956521739,
            0.15989159891598917
          ]
        },
        "title_cov": {
          "mean": 0.0,
          "variance": 0.0,
          "std": 0.0,
          "values": [
            0.0,
            0.0,
            0.0,
            0.0,
            0.0
          ]
        },
        "noloop": {
          "mean": 0.9738337232126051,
          "variance": 6.780106016447046e-05,
          "std": 0.00823413991649829,
          "values": [
            0.9591836734693877,
            0.9772727272727273,
            0.9782608695652174,
            0.9761904761904762,
            0.9782608695652174
          ]
        },
        "ctx_recall": {
          "mean": 0.17196609808242508,
          "variance": 0.0004515369728583566,
          "std": 0.021249399352884227,
          "values": [
            0.14066496163682865,
            0.18435754189944134,
            0.19230769230769232,
            0.1826086956521739,
            0.15989159891598917
          ]
        },
        "nohall": {
          "mean": 0.20505494505494504,
          "variance": 0.006674073179567685,
          "std": 0.08169500094600456,
          "values": [
            0.09999999999999998,
            0.2857142857142857,
            0.15384615384615385,
            0.19999999999999996,
            0.2857142857142857
          ]
        },
        "storyscore": {
          "mean": 0.5733635919620044,
          "variance": 0.00010456784493910735,
          "std": 0.0102258420161426,
          "values": [
            0.5592579232457349,
            0.5795692992609972,
            0.5829879687382624,
            0.5790845162972159,
            0.5659182522678117
          ]
        }
      }
    },
    "satyajit_ray": {
      "event_driven": {
        "n": 5,
        "bertscore": {
          "mean": 0.8248439431190491,
          "variance": 2.7063470184884864e-06,
          "std": 0.0016450978750483165,
          "values": [
            0.8269389867782593,
            0.822342574596405,
            0.8251309394836426,
            0.824691653251648,
            0.8251155614852905
          ]
        },
        "lexical_recall": {
          "mean": 0.15613738450925174,
          "variance": 0.0001940899796447129,
          "std": 0.013931617983734441,
          "values": [
            0.1580246913580247,
            0.17763157894736842,
            0.1392757660167131,
            0.15126050420168066,
            0.1544943820224719
          ]
        },
        "title_cov": {
          "mean": 0.0,
          "variance": 0.0,
          "std": 0.0,
          "values": [
            0.0,
            0.0,
            0.0,
            0.0,
            0.0
          ]
        },
        "noloop": {
          "mean": 0.965818216175359,
          "variance": 0.00015589945875889617,
          "std": 0.012485970477255508,
          "values": [
            0.962962962962963,
            0.95,
            0.9791666666666666,
            0.9777777777777777,
            0.9591836734693877
          ]
        },
        "ctx_recall": {
          "mean": 0.15613738450925174,
          "variance": 0.0001940899796447129,
          "std": 0.013931617983734441,
          "values": [
            0.1580246913580247,
            0.17763157894736842,
            0.1392757660167131,
            0.15126050420168066,
            0.1544943820224719
          ]
        },
        "nohall": {
          "mean": 0.2280861244019139,
          "variance": 0.0024579448193567228,
          "std": 0.049577664520998994,
          "values": [
            0.2272727272727273,
            0.15000000000000002,
            0.2222222222222222,
            0.26315789473684215,
            0.2777777777777778
          ]
        },
        "storyscore": {
          "mean": 0.5573613196751301,
          "variance": 2.5506237124418275e-05,
          "std": 0.005050369998764276,
          "values": [
            0.5593732686101655,
            0.5644581763367904,
            0.5507888700968708,
            0.555319193631661,
            0.5568670897001631
          ]
        }
      },
      "baseline": {
        "n": 5,
        "bertscore": {
          "mean": 0.8269758582115173,
          "variance": 4.483503351799812e-05,
          "std": 0.006695896767274576,
          "values": [
            0.8281064033508301,
            0.8166555166244507,
            0.8261260390281677,
            0.8351920247077942,
            0.828799307346344
          ]
        },
        "lexical_recall": {
          "mean": 0.16264956727215124,
          "variance": 0.00010399719343427713,
          "std": 0.010197901423051565,
          "values": [
            0.16857142857142857,
            0.14555256064690028,
            0.1671309192200557,
            0.17079889807162535,
            0.16119402985074627
          ]
        },
        "title_cov": {
          "mean": 0.0,
          "variance": 0.0,
          "std": 0.0,
          "values": [
            0.0,
            0.0,
            0.0,
            0.0,
            0.0
          ]
        },
        "noloop": {
          "mean": 0.9740826185546683,
          "variance": 9.682643395150781e-05,
          "std": 0.009840042375493503,
          "values": [
            0.9777777777777777,
            0.9795918367346939,
            0.9782608695652174,
            0.9782608695652174,
            0.9565217391304348
          ]
        },
        "ctx_recall": {
          "mean": 0.16264956727215124,
          "variance": 0.00010399719343427713,
          "std": 0.010197901423051565,
          "values": [
            0.16857142857142857,
            0.14555256064690028,
            0.1671309192200557,
            0.17079889807162535,
            0.16119402985074627
          ]
        },
        "nohall": {
          "mean": 0.36023976023976023,
          "variance": 0.007493430645278798,
          "std": 0.08656460388218037,
          "values": [
            0.3076923076923077,
            0.2727272727272727,
            0.36363636363636365,
            0.3571428571428571,
            0.5
          ]
        },
        "storyscore": {
          "mean": 0.5612453418357709,
          "variance": 6.201644718081889e-05,
          "std": 0.007875052201783738,
          "values": [
            0.5642924134390694,
            0.5482143342334305,
            0.5625279911049229,
            0.5694347740533267,
            0.561757196348105
          ]
        }
      }
    },
    "serge_gainsbourg": {
      "event_driven": {
        "n": 5,
        "bertscore": {
          "mean": 0.8315598130226135,
          "variance": 5.281088543540591e-06,
          "std": 0.0022980619102932346,
          "values": [
            0.832687497138977,
            0.8329339027404785,
            0.8338358402252197,
            0.8299987316131592,
            0.8283430933952332
          ]
        },
        "lexical_recall": {
          "mean": 0.12313024332056681,
          "variance": 0.0002604414212465621,
          "std": 0.01613819758357674,
          "values": [
            0.10638297872340426,
            0.14497041420118342,
            0.11801242236024845,
            0.11178247734138973,
            0.13450292397660818
          ]
        },
        "title_cov": {
          "mean": 0.0,
          "variance": 0.0,
          "std": 0.0,
          "values": [
            0.0,
            0.0,
            0.0,
            0.0,
            0.0
          ]
        },
        "noloop": {
          "mean": 0.9596679898174916,
          "variance": 0.00012906748533654164,
          "std": 0.011360787179440588,
          "values": [
            0.9583333333333334,
            0.9545454545454546,
            0.9523809523809523,
            0.9534883720930233,
            0.9795918367346939
          ]
        },
        "ctx_recall": {
          "mean": 0.12313024332056681,
          "variance": 0.0002604414212465621,
          "std": 0.01613819758357674,
          "values": [
            0.10638297872340426,
            0.14497041420118342,
            0.11801242236024845,
            0.11178247734138973,
            0.13450292397660818
          ]
        },
        "nohall": {
          "mean": 0.2050793650793651,
          "variance": 0.01004963466868229,
          "std": 0.10024786615525684,
          "values": [
            0.09999999999999998,
            0.2142857142857143,
            0.33333333333333337,
            0.11111111111111116,
            0.2666666666666667
          ]
        },
        "storyscore": {
          "mean": 0.5481879851417949,
          "variance": 4.124483827524542e-05,
          "std": 0.006422214437033804,
          "values": [
            0.5421656897727479,
            0.5577485073247604,
            0.5475064730792313,
            0.5427122299044513,
            0.5508070256277832
          ]
        }
      },
      "baseline": {
        "n": 5,
        "bertscore": {
          "mean": 0.8359709143638611,
          "variance": 1.7873541598945054e-05,
          "std": 0.004227711153679382,
          "values": [
            0.8388216495513916,
            0.8287964463233948,
            0.8375161290168762,
            0.8390404582023621,
            0.8356798887252808
          ]
        },
        "lexical_recall": {
          "mean": 0.12740964936250243,
          "variance": 8.331683204861654e-05,
          "std": 0.009127805434419411,
          "values": [
            0.12605042016806722,
            0.11290322580645161,
            0.1326530612244898,
            0.1284153005464481,
            0.13702623906705538
          ]
        },
        "title_cov": {
          "mean": 0.0,
          "variance": 0.0,
          "std": 0.0,
          "values": [
            0.0,
            0.0,
            0.0,
            0.0,
            0.0
          ]
        },
        "noloop": {
          "mean": 0.9659599483204134,
          "variance": 0.00012316370543970974,
          "std": 0.011097914463524655,
          "values": [
            0.9767441860465116,
            0.9791666666666666,
            0.96,
            0.9583333333333334,
            0.9555555555555556
          ]
        },
        "ctx_recall": {
          "mean": 0.12740964936250243,
          "variance": 8.331683204861654e-05,
          "std": 0.009127805434419411,
          "values": [
            0.12605042016806722,
            0.11290322580645161,
            0.1326530612244898,
            0.1284153005464481,
            0.13702623906705538
          ]
        },
        "nohall": {
          "mean": 0.3612121212121212,
          "variance": 0.018280073461891647,
          "std": 0.1352038219204311,
          "values": [
            0.5,
            0.19999999999999996,
            0.33333333333333337,
            0.2727272727272727,
            0.5
          ]
        },
        "storyscore": {
          "mean": 0.5525464083633176,
          "variance": 3.279614603560983e-05,
          "std": 0.005726791949740258,
          "values": [
            0.5537131577980619,
            0.5424391581166175,
            0.5555709018999216,
            0.5547903951399964,
            0.5562184288619906
          ]
        }
      }
    },
    "taylor_swift": {
      "event_driven": {
        "n": 5,
        "bertscore": {
          "mean": 0.8357488870620727,
          "variance": 1.2087475295530225e-05,
          "std": 0.0034767046603831945,
          "values": [
            0.836800217628479,
            0.8356194496154785,
            0.8404357433319092,
            0.8351276516914368,
            0.8307613730430603
          ]
        },
        "lexical_recall": {
          "mean": 0.21712152425288855,
          "variance": 0.00020928209827597035,
          "std": 0.01446658557766726,
          "values": [
            0.20710059171597633,
            0.21646341463414634,
            0.24149659863945577,
            0.21518987341772153,
            0.20535714285714285
          ]
        },
        "title_cov": {
          "mean": 0.0,
          "variance": 0.0,
          "std": 0.0,
          "values": [
            0.0,
            0.0,
            0.0,
            0.0,
            0.0
          ]
        },
        "noloop": {
          "mean": 0.9671829073042421,
          "variance": 0.00015048933443249232,
          "std": 0.012267409442604104,
          "values": [
            0.9782608695652174,
            0.9767441860465116,
            0.972972972972973,
            0.9523809523809523,
            0.9555555555555556
          ]
        },
        "ctx_recall": {
          "mean": 0.21712152425288855,
          "variance": 0.00020928209827597035,
          "std": 0.01446658557766726,
          "values": [
            0.20710059171597633,
            0.21646341463414634,
            0.24149659863945577,
            0.21518987341772153,
            0.20535714285714285
          ]
        },
        "nohall": {
          "mean": 0.22999999999999998,
          "variance": 0.024187500000000004,
          "std": 0.15552331014995793,
          "values": [
            0.4,
            0.125,
            0.4,
            0.09999999999999998,
            0.125
          ]
        },
        "storyscore": {
          "mean": 0.588297941938399,
          "variance": 5.7476711053414645e-05,
          "std": 0.00758133966086566,
          "values": [
            0.5849203672634778,
            0.5879570356229455,
            0.6008600854549278,
            0.5871525403819506,
            0.5805996809686933
          ]
        }
      },
      "baseline": {
        "n": 5,
        "bertscore": {
          "mean": 0.8292415618896485,
          "variance": 2.650376998118986e-05,
          "std": 0.005148181230414277,
          "values": [
            0.8305349349975586,
            0.8312442898750305,
            0.8252442479133606,
            0.8231073021888733,
            0.8360770344734192
          ]
        },
        "lexical_recall": {
          "mean": 0.16986569982880567,
          "variance": 8.201231374418859e-05,
          "std": 0.009056065025395334,
          "values": [
            0.1691842900302115,
            0.16374269005847952,
            0.17888563049853373,
            0.1586021505376344,
            0.17891373801916932
          ]
        },
        "title_cov": {
          "mean": 0.0,
          "variance": 0.0,
          "std": 0.0,
          "values": [
            0.0,
            0.0,
            0.0,
            0.0,
            0.0
          ]
        },
        "noloop": {
          "mean": 0.9567733013649493,
          "variance": 7.013304613645621e-06,
          "std": 0.0026482644531174793,
          "values": [
            0.9565217391304348,
            0.9583333333333334,
            0.9574468085106383,
            0.9591836734693877,
            0.9523809523809523
          ]
        },
        "ctx_recall": {
          "mean": 0.16986569982880567,
          "variance": 8.201231374418859e-05,
          "std": 0.009056065025395334,
          "values": [
            0.1691842900302115,
            0.16374269005847952,
            0.17888563049853373,
            0.1586021505376344,
            0.17891373801916932
          ]
        },
        "nohall": {
          "mean": 0.49000000000000005,
          "variance": 0.04050000000000001,
          "std": 0.2012461179749811,
          "values": [
            0.4,
            0.8,
            0.5,
            0.25,
            0.5
          ]
        },
        "storyscore": {
          "mean": 0.5654912170653114,
          "variance": 3.2472321603856566e-05,
          "std": 0.005698449052492842,
          "values": [
            0.5659946770106197,
            0.5642436499484101,
            0.5667008009474298,
            0.5573052415283777,
            0.5732117158917193
          ]
        }
      }
    },
    "vaslav_nijinsky": {
      "event_driven": {
        "n": 5,
        "bertscore": {
          "mean": 0.8410968780517578,
          "variance": 5.788398555139906e-06,
          "std": 0.0024059090912043842,
          "values": [
            0.8418400883674622,
            0.8370768427848816,
            0.8432607650756836,
            0.8408987522125244,
            0.8424079418182373
          ]
        },
        "lexical_recall": {
          "mean": 0.10461515443922151,
          "variance": 9.189791749085853e-05,
          "std": 0.009586340151009589,
          "values": [
            0.11513157894736842,
            0.08970099667774087,
            0.11041009463722397,
            0.10397553516819572,
            0.10385756676557864
          ]
        },
        "title_cov": {
          "mean": 0.0,
          "variance": 0.0,
          "std": 0.0,
          "values": [
            0.0,
            0.0,
            0.0,
            0.0,
            0.0
          ]
        },
        "noloop": {
          "mean": 0.956558917817499,
          "variance": 0.00011209551580102662,
          "std": 0.010587516979964028,
          "values": [
            0.9473684210526316,
            0.9743589743589743,
            0.95,
            0.9545454545454546,
            0.9565217391304348
          ]
        },
        "ctx_recall": {
          "mean": 0.10461515443922151,
          "variance": 9.189791749085853e-05,
          "std": 0.009586340151009589,
          "values": [
            0.11513157894736842,
            0.08970099667774087,
            0.11041009463722397,
            0.10397553516819572,
            0.10385756676557864
          ]
        },
        "nohall": {
          "mean": 0.04913419913419914,
          "variance": 0.0020600251119731647,
          "std": 0.045387499512235356,
          "values": [
            0.0,
            0.09090909090909094,
            0.0714285714285714,
            0.0,
            0.08333333333333337
          ]
        },
        "storyscore": {
          "mean": 0.5465041886067433,
          "variance": 2.6320821951657997e-05,
          "std": 0.005130382242256224,
          "values": [
            0.5511566845994246,
            0.5381265043420254,
            0.5501204969002997,
            0.5461294653947929,
            0.5469877917971738
          ]
        }
      },
      "baseline": {
        "n": 5,
        "bertscore": {
          "mean": 0.8448609709739685,
          "variance": 2.3393254195980262e-05,
          "std": 0.004836657337043866,
          "values": [
            0.8509055376052856,
            0.8460012674331665,
            0.8413509130477905,
            0.8473051190376282,
            0.8387420177459717
          ]
        },
        "lexical_recall": {
          "mean": 0.09279925768597949,
          "variance": 7.554209115381254e-05,
          "std": 0.008691495334740309,
          "values": [
            0.1005586592178771,
            0.09171597633136094,
            0.08259587020648967,
            0.10263929618768329,
            0.08648648648648649
          ]
        },
        "title_cov": {
          "mean": 0.0,
          "variance": 0.0,
          "std": 0.0,
          "values": [
            0.0,
            0.0,
            0.0,
            0.0,
            0.0
          ]
        },
        "noloop": {
          "mean": 0.9694034023818799,
          "variance": 0.00012261845618067582,
          "std": 0.011073321822320339,
          "values": [
            0.9555555555555556,
            0.9767441860465116,
            0.9782608695652174,
            0.9772727272727273,
            0.9591836734693877
          ]
        },
        "ctx_recall": {
          "mean": 0.09279925768597949,
          "variance": 7.554209115381254e-05,
          "std": 0.008691495334740309,
          "values": [
            0.1005586592178771,
            0.09171597633136094,
            0.08259587020648967,
            0.10263929618768329,
            0.08648648648648649
          ]
        },
        "nohall": {
          "mean": 0.088975468975469,
          "variance": 0.0028587836726364883,
          "std": 0.053467594603053614,
          "values": [
            0.1428571428571429,
            0.09999999999999998,
            0.0,
            0.09090909090909094,
            0.11111111111111116
          ]
        },
        "storyscore": {
          "mean": 0.5440362856587729,
          "variance": 3.780744628008033e-05,
          "std": 0.006148775998528514,
          "values": [
            0.5507667862503222,
            0.5442871509924443,
            0.5378488959112702,
            0.5494387898976502,
            0.5378398052421776
          ]
        }
      }
    },
    "vincent_van_gogh": {
      "event_driven": {
        "n": 5,
        "bertscore": {
          "mean": 0.8430763125419617,
          "variance": 1.0549665247339134e-05,
          "std": 0.0032480248224635126,
          "values": [
            0.8449691534042358,
            0.8375553488731384,
            0.843802809715271,
            0.8432238101959229,
            0.8458304405212402
          ]
        },
        "lexical_recall": {
          "mean": 0.2508571182015605,
          "variance": 0.0001779998102266777,
          "std": 0.013341656952068499,
          "values": [
            0.2514792899408284,
            0.23006134969325154,
            0.24814814814814815,
            0.26006191950464397,
            0.26453488372093026
          ]
        },
        "title_cov": {
          "mean": 0.0,
          "variance": 0.0,
          "std": 0.0,
          "values": [
            0.0,
            0.0,
            0.0,
            0.0,
            0.0
          ]
        },
        "noloop": {
          "mean": 0.9271498712348055,
          "variance": 0.0018602098180052942,
          "std": 0.04313014975635135,
          "values": [
            0.9767441860465116,
            0.9069767441860466,
            0.8648648648648649,
            0.9523809523809523,
            0.9347826086956522
          ]
        },
        "ctx_recall": {
          "mean": 0.2508571182015605,
          "variance": 0.0001779998102266777,
          "std": 0.013341656952068499,
          "values": [
            0.2514792899408284,
            0.23006134969325154,
            0.24814814814814815,
            0.26006191950464397,
            0.26453488372093026
          ]
        },
        "nohall": {
          "mean": 0.19564804390655785,
          "variance": 0.0022359597571739247,
          "std": 0.047285936145686325,
          "values": [
            0.1875,
            0.21052631578947367,
            0.23529411764705888,
            0.11764705882352944,
            0.2272727272727273
          ]
        },
        "storyscore": {
          "mean": 0.6061886348058012,
          "variance": 5.0643884970868054e-05,
          "std": 0.007116451712115249,
          "values": [
            0.6075732080188729,
            0.5945577492011836,
            0.6055409450884218,
            0.6099590539194113,
            0.6133122178011162
          ]
        }
      },
      "baseline": {
        "n": 5,
        "bertscore": {
          "mean": 0.8438137531280517,
          "variance": 8.348280906744777e-06,
          "std": 0.0028893391816719573,
          "values": [
            0.8476483225822449,
            0.8400443196296692,
            0.8422344326972961,
            0.8452188968658447,
            0.8439227938652039
          ]
        },
        "lexical_recall": {
          "mean": 0.23086911498594254,
          "variance": 0.00024281831828967446,
          "std": 0.01558262873489818,
          "values": [
            0.23939393939393938,
            0.2204724409448819,
            0.21329639889196675,
            0.22849462365591397,
            0.25268817204301075
          ]
        },
        "title_cov": {
          "mean": 0.0,
          "variance": 0.0,
          "std": 0.0,
          "values": [
            0.0,
            0.0,
            0.0,
            0.0,
            0.0
          ]
        },
        "noloop": {
          "mean": 0.9318946975128497,
          "variance": 0.0004035518585696325,
          "std": 0.0200886002142915,
          "values": [
            0.9069767441860466,
            0.9591836734693877,
            0.9361702127659575,
            0.9183673469387755,
            0.9387755102040817
          ]
        },
        "ctx_recall": {
          "mean": 0.23086911498594254,
          "variance": 0.00024281831828967446,
          "std": 0.01558262873489818,
          "values": [
            0.23939393939393938,
            0.2204724409448819,
            0.21329639889196675,
            0.22849462365591397,
            0.25268817204301075
          ]
        },
        "nohall": {
          "mean": 0.35021645021645026,
          "variance": 0.00024456063417102315,
          "std": 0.015638434517912053,
          "values": [
            0.33333333333333337,
            0.36363636363636365,
            0.36363636363636365,
            0.33333333333333337,
            0.3571428571428571
          ]
        },
        "storyscore": {
          "mean": 0.5986358978712081,
          "variance": 5.3697218053550664e-05,
          "std": 0.0073278385662861505,
          "values": [
            0.6043465693069228,
            0.5922155681557543,
            0.5906592191751644,
            0.5985291875818725,
            0.6074289451363266
          ]
        }
      }
    },
    "wolfgang_amadeus_mozart": {
      "event_driven": {
        "n": 5,
        "bertscore": {
          "mean": 0.8472941517829895,
          "variance": 5.191962948458695e-06,
          "std": 0.0022785879286212974,
          "values": [
            0.8488825559616089,
            0.846843957901001,
            0.8449129462242126,
            0.8503239154815674,
            0.8455073833465576
          ]
        },
        "lexical_recall": {
          "mean": 0.17586644887821637,
          "variance": 0.00021281922456782803,
          "std": 0.014588324940438777,
          "values": [
            0.16666666666666666,
            0.19130434782608696,
            0.1564245810055866,
            0.17684887459807075,
            0.18808777429467086
          ]
        },
        "title_cov": {
          "mean": 0.0,
          "variance": 0.0,
          "std": 0.0,
          "values": [
            0.0,
            0.0,
            0.0,
            0.0,
            0.0
          ]
        },
        "noloop": {
          "mean": 0.966815702028468,
          "variance": 0.00015094426703918398,
          "std": 0.012285937776140003,
          "values": [
            0.975,
            0.9772727272727273,
            0.9574468085106383,
            0.95,
            0.9743589743589743
          ]
        },
        "ctx_recall": {
          "mean": 0.17586644887821637,
          "variance": 0.00021281922456782803,
          "std": 0.014588324940438777,
          "values": [
            0.16666666666666666,
            0.19130434782608696,
            0.1564245810055866,
            0.17684887459807075,
            0.18808777429467086
          ]
        },
        "nohall": {
          "mean": 0.2575954592363261,
          "variance": 0.0031651319916375675,
          "std": 0.05625950578913369,
          "values": [
            0.19999999999999996,
            0.21052631578947367,
            0.25,
            0.33333333333333337,
            0.2941176470588235
          ]
        },
        "storyscore": {
          "mean": 0.5787230706210802,
          "variance": 3.662481094798828e-05,
          "std": 0.006051843599101705,
          "values": [
            0.575996200243632,
            0.5846281138710354,
            0.5695176001367622,
            0.5809338991281686,
            0.5825395397258029
          ]
        }
      },
      "baseline": {
        "n": 5,
        "bertscore": {
          "mean": 0.8471492409706116,
          "variance": 2.0121568074671358e-05,
          "std": 0.00448570708748034,
          "values": [
            0.8421312570571899,
            0.8538986444473267,
            0.845794677734375,
            0.848941445350647,
            0.8449801802635193
          ]
        },
        "lexical_recall": {
          "mean": 0.15746636261207336,
          "variance": 0.0003253025087196448,
          "std": 0.018036144508171495,
          "values": [
            0.12682926829268293,
            0.17045454545454544,
            0.17105263157894737,
            0.15877437325905291,
            0.16022099447513813
          ]
        },
        "title_cov": {
          "mean": 0.0,
          "variance": 0.0,
          "std": 0.0,
          "values": [
            0.0,
            0.0,
            0.0,
            0.0,
            0.0
          ]
        },
        "noloop": {
          "mean": 0.9732065271808347,
          "variance": 0.00011483699948860542,
          "std": 0.010716202661792348,
          "values": [
            0.9811320754716981,
            0.9772727272727273,
            0.9743589743589743,
            0.9787234042553191,
            0.9545454545454546
          ]
        },
        "ctx_recall": {
          "mean": 0.15746636261207336,
          "variance": 0.0003253025087196448,
          "std": 0.018036144508171495,
          "values": [
            0.12682926829268293,
            0.17045454545454544,
            0.17105263157894737,
            0.15877437325905291,
            0.16022099447513813
          ]
        },
        "nohall": {
          "mean": 0.4203174603174603,
          "variance": 0.007937011841773745,
          "std": 0.08908990875387485,
          "values": [
            0.3571428571428571,
            0.4444444444444444,
            0.30000000000000004,
            0.5,
            0.5
          ]
        },
        "storyscore": {
          "mean": 0.5712760896271962,
          "variance": 8.561593363350819e-05,
          "std": 0.00925288785371941,
          "values": [
            0.5560104615513871,
            0.5805210048502141,
            0.5758978592722039,
            0.5728746165140094,
            0.5710765059481668
          ]
        }
      }
    }
  },
  "global": {
    "event_driven": {
      "bertscore": {
        "mean_of_means": 0.8349168032407761,
        "mean_of_variances": 1.8566296076656388e-05,
        "std_of_means": 0.01121036022933785
      },
      "lexical_recall": {
        "mean_of_means": 0.1751902773739703,
        "mean_of_variances": 0.00021035654091816608,
        "std_of_means": 0.07214571866303247
      },
      "title_cov": {
        "mean_of_means": 0.0,
        "mean_of_variances": 0.0,
        "std_of_means": 0.0
      },
      "noloop": {
        "mean_of_means": 0.953373736847027,
        "mean_of_variances": 0.000493866022481306,
        "std_of_means": 0.02547534035379195
      },
      "ctx_recall": {
        "mean_of_means": 0.1751902773739703,
        "mean_of_variances": 0.00021035654091816608,
        "std_of_means": 0.07214571866303247
      },
      "nohall": {
        "mean_of_means": 0.22554007491327116,
        "mean_of_variances": 0.005398404239979266,
        "std_of_means": 0.1342629166580267
      },
      "storyscore": {
        "mean_of_means": 0.5710261928940538,
        "mean_of_variances": 5.559106289149825e-05,
        "std_of_means": 0.03309881344685328
      }
    },
    "baseline": {
      "bertscore": {
        "mean_of_means": 0.8333364897966385,
        "mean_of_variances": 1.747332122297607e-05,
        "std_of_means": 0.012083941163558593
      },
      "lexical_recall": {
        "mean_of_means": 0.1542244288054434,
        "mean_of_variances": 0.000245425693109176,
        "std_of_means": 0.060870864538118255
      },
      "title_cov": {
        "mean_of_means": 0.0,
        "mean_of_variances": 0.0,
        "std_of_means": 0.0
      },
      "noloop": {
        "mean_of_means": 0.9646696735526739,
        "mean_of_variances": 0.00014263260720241146,
        "std_of_means": 0.011209784200600398
      },
      "ctx_recall": {
        "mean_of_means": 0.1542244288054434,
        "mean_of_variances": 0.000245425693109176,
        "std_of_means": 0.060870864538118255
      },
      "nohall": {
        "mean_of_means": 0.29863337724367134,
        "mean_of_variances": 0.009075216659891232,
        "std_of_means": 0.15776982479049587
      },
      "storyscore": {
        "mean_of_means": 0.5616916654001605,
        "mean_of_variances": 6.391342120458908e-05,
        "std_of_means": 0.028395737767310844
      }
    },
    "n_entities": 20
  }
}